README
setup.py
distcontrib/__init__.py
distcontrib/bootstrap.py
distcontrib/tools.py
distcontrib.egg-info/PKG-INFO
distcontrib.egg-info/SOURCES.txt
distcontrib.egg-info/dependency_links.txt
distcontrib.egg-info/not-zip-safe
distcontrib.egg-info/requires.txt
distcontrib.egg-info/top_level.txt
distcontrib/command/__init__.py
distcontrib/command/doctest.py
distcontrib/command/zap.py